gym_3d_connectX/__init__.py
3d_connectX_env-1.0.1.dist-info/LICENSE
3d_connectX_env-1.0.1.dist-info/METADATA
3d_connectX_env-1.0.1.dist-info/WHEEL
3d_connectX_env-1.0.1.dist-info/top_level.txt
3d_connectX_env-1.0.1.dist-info/RECORD
