Metadata-Version: 2.1
Name: 3d-connectX-env
Version: 1.0.1
Summary: 3D ConnectX for OpenAI Gym.
Home-page: https://github.com/youngeek-0410/3d-connectX-env
Author: Ryusei Ito
Author-email: 31807@toyota.kosen-ac.jp
License: UNKNOWN
Platform: UNKNOWN
Requires-Python: >=3.7
License-File: LICENSE
Requires-Dist: numpy (~=1.20.3)
Requires-Dist: gym (~=0.18.3)
Requires-Dist: torch (~=1.9.0)
Requires-Dist: pandas (~=1.2.4)
Requires-Dist: plotly (~=4.14.3)
